sdk/channel.py
sdk/channel_invite.py
sdk/channel_tag.py
sdk/channel_update.py
sdk/client.py
sdk/error.py
sdk/error_exception.py
sdk/message.py
sdk/message_allowed_mentions.py
sdk/message_embed.py
sdk/message_reference.py
sdk/message_tag.py
sdk/user.py
sdk/user_tag.py
sdkfabric_discord-0.2.11.dist-info/LICENSE
sdkfabric_discord-0.2.11.dist-info/METADATA
sdkfabric_discord-0.2.11.dist-info/WHEEL
sdkfabric_discord-0.2.11.dist-info/top_level.txt
sdkfabric_discord-0.2.11.dist-info/RECORD
